README.rst
setup.cfg
setup.py
cyclotron_aio/__init__.py
cyclotron_aio/http.py
cyclotron_aio/httpd.py
cyclotron_aio/runner.py
cyclotron_aio/stop.py
cyclotron_aio.egg-info/PKG-INFO
cyclotron_aio.egg-info/SOURCES.txt
cyclotron_aio.egg-info/dependency_links.txt
cyclotron_aio.egg-info/requires.txt
cyclotron_aio.egg-info/top_level.txt
test/__init__.py
test/test_http_client.py
test/test_httpd.py
test/test_runner.py
test/test_stop.py