Metadata-Version: 1.1
Name: cyclotron-aio
Version: 0.7.0
Summary: Asynchronous IO drivers for cyclotron
Home-page: https://github.com/MainRo/cyclotron-aio.git
Author: Romain Picard
Author-email: romain.picard@oakbits.com
License: MIT
Platform: any
Classifier: Development Status :: 3 - Alpha
Classifier: License :: OSI Approved :: MIT License
Classifier: Intended Audience :: Developers
Classifier: Programming Language :: Python :: 3
